LICENSE
README.rst
setup.py
LeerImagenes/LeerImagenes.py
LeerImagenes/__init__.py
LeerImagenes/_binary.py
LeerImagenes.egg-info/PKG-INFO
LeerImagenes.egg-info/SOURCES.txt
LeerImagenes.egg-info/dependency_links.txt
LeerImagenes.egg-info/top_level.txt