Metadata-Version: 2.1
Name: LeerImagenes
Version: 1.0.1
Summary: Light image reader   |   Lector ligero de imagenes
Home-page: https://github.com/ZaimirPuerta
Download-URL: https://github.com/ZaimirPuerta/LeerImagenes/
Author: Zaimir
Author-email: zaimirpuerta2711@gmail.com
License: MIT License
Keywords: LeerImagenes,Leer,Imagenes,leer,imagenes,read,images
License-File: LICENSE
